CONTRIBUTING.rst
LICENSE
MANIFEST.in
README.rst
setup.cfg
setup.py
tox.ini
vendor.py
ceph_deploy/__init__.py
ceph_deploy/admin.py
ceph_deploy/calamari.py
ceph_deploy/cli.py
ceph_deploy/cliutil.py
ceph_deploy/config.py
ceph_deploy/connection.py
ceph_deploy/exc.py
ceph_deploy/forgetkeys.py
ceph_deploy/gatherkeys.py
ceph_deploy/install.py
ceph_deploy/mds.py
ceph_deploy/mgr.py
ceph_deploy/misc.py
ceph_deploy/mon.py
ceph_deploy/new.py
ceph_deploy/osd.py
ceph_deploy/pkg.py
ceph_deploy/repo.py
ceph_deploy/rgw.py
ceph_deploy/validate.py
ceph_deploy.egg-info/PKG-INFO
ceph_deploy.egg-info/SOURCES.txt
ceph_deploy.egg-info/dependency_links.txt
ceph_deploy.egg-info/entry_points.txt
ceph_deploy.egg-info/requires.txt
ceph_deploy.egg-info/top_level.txt
ceph_deploy/conf/__init__.py
ceph_deploy/conf/ceph.py
ceph_deploy/conf/cephdeploy.py
ceph_deploy/hosts/__init__.py
ceph_deploy/hosts/common.py
ceph_deploy/hosts/remotes.py
ceph_deploy/hosts/util.py
ceph_deploy/hosts/arch/__init__.py
ceph_deploy/hosts/arch/install.py
ceph_deploy/hosts/arch/uninstall.py
ceph_deploy/hosts/arch/mon/__init__.py
ceph_deploy/hosts/centos/__init__.py
ceph_deploy/hosts/centos/install.py
ceph_deploy/hosts/centos/uninstall.py
ceph_deploy/hosts/centos/mon/__init__.py
ceph_deploy/hosts/debian/__init__.py
ceph_deploy/hosts/debian/install.py
ceph_deploy/hosts/debian/uninstall.py
ceph_deploy/hosts/debian/mon/__init__.py
ceph_deploy/hosts/fedora/__init__.py
ceph_deploy/hosts/fedora/install.py
ceph_deploy/hosts/fedora/uninstall.py
ceph_deploy/hosts/fedora/mon/__init__.py
ceph_deploy/hosts/rhel/__init__.py
ceph_deploy/hosts/rhel/install.py
ceph_deploy/hosts/rhel/uninstall.py
ceph_deploy/hosts/rhel/mon/__init__.py
ceph_deploy/hosts/suse/__init__.py
ceph_deploy/hosts/suse/install.py
ceph_deploy/hosts/suse/uninstall.py
ceph_deploy/hosts/suse/mon/__init__.py
ceph_deploy/lib/__init__.py
ceph_deploy/lib/vendor/__init__.py
ceph_deploy/lib/vendor/remoto/__init__.py
ceph_deploy/lib/vendor/remoto/connection.py
ceph_deploy/lib/vendor/remoto/exc.py
ceph_deploy/lib/vendor/remoto/file_sync.py
ceph_deploy/lib/vendor/remoto/log.py
ceph_deploy/lib/vendor/remoto/process.py
ceph_deploy/lib/vendor/remoto/util.py
