Metadata-Version: 1.0
Name: ceph-deploy
Version: 2.0.1
Summary: Deploy Ceph with minimal infrastructure
Home-page: https://github.com/ceph/ceph-deploy
Author: Inktank
Author-email: ceph-devel@vger.kernel.org
License: MIT
Keywords: ceph deploy
Platform: UNKNOWN
